<?xml version="1.0" encoding="utf-8" ?>
<dwsync>
<file name="font-awesome.css" server="marksanderson.org//web/marksanderson.org/public/" local="132662149990853000" remote="132662152570000000" Dst="1" />
<file name="font-awesome.scss" server="marksanderson.org//web/marksanderson.org/public/" local="132662149943434697" remote="132662152580000000" Dst="1" />
<file name="_animated.scss" server="marksanderson.org//web/marksanderson.org/public/" local="132662149944665825" remote="132662152590000000" Dst="1" />
<file name="_bordered-pulled.scss" server="marksanderson.org//web/marksanderson.org/public/" local="132662149945126240" remote="132662152600000000" Dst="1" />
<file name="_core.scss" server="marksanderson.org//web/marksanderson.org/public/" local="132662149944355542" remote="132662152610000000" Dst="1" />
<file name="_fixed-width.scss" server="marksanderson.org//web/marksanderson.org/public/" local="132662149944976102" remote="132662152610000000" Dst="1" />
<file name="_icons.scss" server="marksanderson.org//web/marksanderson.org/public/" local="132662149944815963" remote="132662152620000000" Dst="1" />
<file name="_larger.scss" server="marksanderson.org//web/marksanderson.org/public/" local="132662149944205473" remote="132662152630000000" Dst="1" />
<file name="_list.scss" server="marksanderson.org//web/marksanderson.org/public/" local="132662149943905129" remote="132662152640000000" Dst="1" />
<file name="_mixins.scss" server="marksanderson.org//web/marksanderson.org/public/" local="132662149944515684" remote="132662152650000000" Dst="1" />
<file name="_path.scss" server="marksanderson.org//web/marksanderson.org/public/" local="132662149943754991" remote="132662152660000000" Dst="1" />
<file name="_rotated-flipped.scss" server="marksanderson.org//web/marksanderson.org/public/" local="132662149943594846" remote="132662152670000000" Dst="1" />
<file name="_screen-reader.scss" server="marksanderson.org//web/marksanderson.org/public/" local="132662149944055264" remote="132662152680000000" Dst="1" />
<file name="_stacked.scss" server="marksanderson.org//web/marksanderson.org/public/" local="132662149943114408" remote="132662152690000000" Dst="1" />
<file name="_variables.scss" server="marksanderson.org//web/marksanderson.org/public/" local="132662149943294573" remote="132662152700000000" Dst="1" />
</dwsync>